gazelle_client.py
gazelle_client-1.0.1.dist-info/LICENSE
gazelle_client-1.0.1.dist-info/METADATA
gazelle_client-1.0.1.dist-info/WHEEL
gazelle_client-1.0.1.dist-info/top_level.txt
gazelle_client-1.0.1.dist-info/RECORD
