Metadata-Version: 2.1
Name: gazelle-client
Version: 1.0.1
Summary: Python API for Gazelle
Home-page: https://github.com/hibikidesu/gazelle_api_py
Author: Hibiki
License: UNKNOWN
Platform: UNKNOWN
Classifier: Intended Audience :: Developers
Classifier: Topic :: Software Development :: Libraries
Classifier: Topic :: Software Development :: Libraries :: Python Modules
Classifier: Topic :: Utilities
Requires-Python: >=3.7
License-File: LICENSE
Requires-Dist: requests
Requires-Dist: appdirs
